songpal/__init__.py
songpal/common.py
songpal/containers.py
songpal/device.py
songpal/discovery.py
songpal/group.py
songpal/main.py
songpal/method.py
songpal/notification.py
songpal/service.py
songpal/version.py
python_songpal-0.16.1.dist-info/LICENSE
python_songpal-0.16.1.dist-info/METADATA
python_songpal-0.16.1.dist-info/WHEEL
python_songpal-0.16.1.dist-info/entry_points.txt
python_songpal-0.16.1.dist-info/RECORD
