Metadata-Version: 2.1
Name: python-songpal
Version: 0.16.1
Summary: Python library for interfacing with Sony's Songpal devices
Home-page: https://github.com/rytilahti/python-songpal
License: GPL-3.0
Author: Teemu R
Author-email: tpr@iki.fi
Requires-Python: >=3.8,<4.0
Classifier: License :: OSI Approved :: GNU General Public License v3 (GPLv3)
Classifier: Programming Language :: Python :: 3
Classifier: Programming Language :: Python :: 3.8
Classifier: Programming Language :: Python :: 3.9
Classifier: Programming Language :: Python :: 3.10
Classifier: Programming Language :: Python :: 3.11
Classifier: Programming Language :: Python :: 3.12
Requires-Dist: aiohttp
Requires-Dist: async_upnp_client (>=0.32)
Requires-Dist: attrs
Requires-Dist: click (>=8)
Project-URL: Repository, https://github.com/rytilahti/python-songpal
